[
    {
        "id": 1,
        "text": "क्या आप कई लोगों के साथ संपर्क में आकर ऊर्जा महसूस करते हैं।",
        "analytic_id": 1,
        "question_id": 1
    },
    {
        "id": 2,
        "text": "क्या आप लंबे सामाजिक संपर्क के बाद थका हुआ महसूस करते हैं।",
        "analytic_id": 2,
        "question_id": 1
    },
    {
        "id": 3,
        "text": "दोस्तों और परिवार के साथ गतिविधियों में भाग लेना।",
        "analytic_id": 1,
        "question_id": 2
    },
    {
        "id": 4,
        "text": "एक करीबी दोस्त के साथ अकेले या समय बिताना।",
        "analytic_id": 2,
        "question_id": 2
    },
    {
        "id": 5,
        "text": "जोर से सोचते हुए और दूसरों के साथ विचारों पर चर्चा करना।",
        "analytic_id": 1,
        "question_id": 3
    },
    {
        "id": 6,
        "text": "विचारों को साझा करने से पहले आंतरिक रूप से संसाधित करना।",
        "analytic_id": 2,
        "question_id": 3
    },
    {
        "id": 7,
        "text": "विवरण और तथ्यों पर ध्यान केंद्रित करना।",
        "analytic_id": 3,
        "question_id": 4
    },
    {
        "id": 8,
        "text": "नीतियों और सिद्धांतों की समझ।",
        "analytic_id": 4,
        "question_id": 4
    },
    {
        "id": 9,
        "text": "जो अब हो रहा है और यथार्थवादी है, उस पर ध्यान केंद्रित करना।",
        "analytic_id": 3,
        "question_id": 5
    },
    {
        "id": 10,
        "text": "भविष्य की संभावनाओं और जो हो सकता है, उस पर विचार करना।",
        "analytic_id": 4,
        "question_id": 5
    },
    {
        "id": 11,
        "text": "पुरानी अनुभवों और व्यावहारिक समाधानों पर भरोसा करना।",
        "analytic_id": 3,
        "question_id": 6
    },
    {
        "id": 12,
        "text": "नई विचारों और नवाचार समाधानों की तलाश में।",
        "analytic_id": 4,
        "question_id": 6
    },
    {
        "id": 13,
        "text": "तर्कसंगत विश्लेषण और वस्तुनिष्ठ मानदंड।",
        "analytic_id": 5,
        "question_id": 7
    },
    {
        "id": 14,
        "text": "व्यक्तिगत मूल्य और दूसरों पर प्रभाव।",
        "analytic_id": 6,
        "question_id": 7
    },
    {
        "id": 15,
        "text": "अपने निर्णयों में दृढ़ और निष्पक्ष होना।",
        "analytic_id": 5,
        "question_id": 8
    },
    {
        "id": 16,
        "text": "लोगों की भावनाओं के प्रति सहानुभूतिपूर्ण और विचारशील होना।",
        "analytic_id": 6,
        "question_id": 8
    },
    {
        "id": 17,
        "text": "समस्या को तर्कसंगत तरीके से हल करने पर ध्यान केंद्रित करना।",
        "analytic_id": 5,
        "question_id": 9
    },
    {
        "id": 18,
        "text": "संतुलन बनाए रखने और दूसरों को चोट न पहुँचाने की कोशिश करना।",
        "analytic_id": 6,
        "question_id": 9
    },
    {
        "id": 19,
        "text": "एक स्पष्ट योजना होना और उस पर टिके रहना।",
        "analytic_id": 7,
        "question_id": 10
    },
    {
        "id": 20,
        "text": "अपने योजनाओं में स्वाभाविक और लचीला होना।",
        "analytic_id": 8,
        "question_id": 10
    },
    {
        "id": 21,
        "text": "आपको प्राथमिकता देना पसंद है कि कार्य पहले से किए जाएं।",
        "analytic_id": 7,
        "question_id": 11
    },
    {
        "id": 22,
        "text": "आपको अंतिम मिनट में काम करना पसंद है।",
        "analytic_id": 8,
        "question_id": 11
    },
    {
        "id": 23,
        "text": "आप चीजों को निश्चित और पूरा करना चाहते हैं।",
        "analytic_id": 7,
        "question_id": 12
    },
    {
        "id": 24,
        "text": "आप विकल्पों को खुला रखने और नई संभावनाओं की खोज में आनंद लेते हैं।",
        "analytic_id": 8,
        "question_id": 12
    }
]
